pynations/CountryInfo.py
pynations/__init__.py
pynations/__main__.py
pynations/cli.py
pynations/geodownloader.py
pynations/geosqlite.py
pynations/data/countryinfo.json
pynations/data/countrylookup.json
pynations/data/geonamesdata/readme.md
pynations-0.0.2.dist-info/AUTHORS.rst
pynations-0.0.2.dist-info/LICENSE
pynations-0.0.2.dist-info/METADATA
pynations-0.0.2.dist-info/WHEEL
pynations-0.0.2.dist-info/entry_points.txt
pynations-0.0.2.dist-info/top_level.txt
pynations-0.0.2.dist-info/RECORD
