Metadata-Version: 2.1
Name: pynations
Version: 0.0.2
Summary: A python library to get information on countries
Home-page: https://github.com/suvinks/python-pynations
Author: Suvin Kannappil Sethumadhavan
Author-email: suvinks@gmail.com
License: MIT
Project-URL: Documentation, https://python-pynations.readthedocs.io/
Project-URL: Changelog, https://python-pynations.readthedocs.io/en/latest/changelog.html
Project-URL: Issue Tracker, https://github.com/suvinks/python-pynations/issues
Platform: UNKNOWN
Classifier: Development Status :: 5 - Production/Stable
Classifier: Intended Audience :: Developers
Classifier: License :: OSI Approved :: MIT License
Classifier: Operating System :: Unix
Classifier: Operating System :: POSIX
Classifier: Operating System :: Microsoft :: Windows
Classifier: Programming Language :: Python
Classifier: Programming Language :: Python :: 3.6
Classifier: Programming Language :: Python :: 3.7
Classifier: Programming Language :: Python :: 3.8
Classifier: Programming Language :: Python :: Implementation :: CPython
Classifier: Programming Language :: Python :: Implementation :: PyPy
Classifier: Topic :: Utilities
Requires-Python: >=3, !=3.0.*, !=3.1.*, !=3.2.*, !=3.3.*, !=3.4.*, !=3.5.*
Requires-Dist: tqdm (>=4.0)
Requires-Dist: Unidecode (>=1.0)
Requires-Dist: requests (>=2.0)
Requires-Dist: Menu (>=3.0)
